flake8_nitpick/__init__.py
flake8_nitpick/config.py
flake8_nitpick/constants.py
flake8_nitpick/files/__init__.py
flake8_nitpick/files/base.py
flake8_nitpick/files/pre_commit.py
flake8_nitpick/files/pyproject_toml.py
flake8_nitpick/files/setup_cfg.py
flake8_nitpick/generic.py
flake8_nitpick/mixin.py
flake8_nitpick/plugin.py
flake8_nitpick/style.py
flake8_nitpick/typedefs.py
flake8_nitpick-0.13.2.dist-info/entry_points.txt
flake8_nitpick-0.13.2.dist-info/LICENSE
flake8_nitpick-0.13.2.dist-info/WHEEL
flake8_nitpick-0.13.2.dist-info/METADATA
flake8_nitpick-0.13.2.dist-info/RECORD
